README.md
setup.py
algorithms/__init__.py
algorithms/array.py
algorithms/convert.py
algorithms/numbers.py
algorithms/polygon.py
algorithms/strings.py
algorithms/utils.py
putlity.egg-info/PKG-INFO
putlity.egg-info/SOURCES.txt
putlity.egg-info/dependency_links.txt
putlity.egg-info/not-zip-safe
putlity.egg-info/top_level.txt