Metadata-Version: 1.0
Name: putlity
Version: 0.1
Summary: Simple python utility library
Home-page: UNKNOWN
Author: Pranav Baburaj
Author-email: UNKNOWN
License: MIT
Platform: UNKNOWN
